{
    "function684485": {
        "filename": "./function684485_explored_schedules.json",
        "node_name": "lanka16",
        "parameters": {
            "beam_size": 2,
            "max_depth": 6
        },
        "program_annotation": {
            "memory_size": 16.0,
            "iterators": {
                "i0": {
                    "lower_bound": 0,
                    "upper_bound": 512,
                    "parent_iterator": null,
                    "child_iterators": [
                        "i1"
                    ],
                    "computations_list": []
                },
                "i1": {
                    "lower_bound": 0,
                    "upper_bound": 16,
                    "parent_iterator": "i0",
                    "child_iterators": [
                        "i2"
                    ],
                    "computations_list": []
                },
                "i2": {
                    "lower_bound": 0,
                    "upper_bound": 256,
                    "parent_iterator": "i1",
                    "child_iterators": [],
                    "computations_list": [
                        "comp00"
                    ]
                }
            },
            "computations": {
                "comp00": {
                    "absolute_order": 1,
                    "iterators": [
                        "i0",
                        "i1",
                        "i2"
                    ],
                    "comp_is_reduction": false,
                    "number_of_additions": 1,
                    "number_of_subtraction": 0,
                    "number_of_multiplication": 0,
                    "number_of_division": 0,
                    "write_access_relation": "{ comp00[i0, i1, i2] -> buf00[i0' = i0, i1' = i1, i2' = i2] }",
                    "write_buffer_id": 0,
                    "data_type": "float64",
                    "data_type_size": 0,
                    "accesses": [
                        {
                            "access_is_reduction": true,
                            "buffer_id": 0,
                            "access_matrix": [
                                [
                                    1,
                                    0,
                                    0,
                                    0
                                ],
                                [
                                    0,
                                    1,
                                    0,
                                    0
                                ],
                                [
                                    0,
                                    0,
                                    1,
                                    0
                                ]
                            ]
                        }
                    ],
                    "expression_representation": {
                        "expr_type": "add",
                        "children": [
                            {
                                "expr_type": "access",
                                "children": []
                            },
                            {
                                "expr_type": "value",
                                "children": []
                            }
                        ]
                    }
                }
            }
        },
        "initial_execution_time": 1.83691,
        "schedules_list": [
            {
                "comp00": {
                    "tiling": {},
                    "unrolling_factor": null,
                    "parallelized_dim": null,
                    "shiftings": null,
                    "transformations_list": []
                },
                "unfuse_iterators": [],
                "tree_structure": {
                    "roots": [
                        {
                            "loop_name": "i0",
                            "computations_list": [],
                            "child_list": [
                                {
                                    "loop_name": "i1",
                                    "computations_list": [],
                                    "child_list": [
                                        {
                                            "loop_name": "i2",
                                            "computations_list": [
                                                "comp00"
                                            ],
                                            "child_list": []
                                        }
                                    ]
                                }
                            ]
                        }
                    ]
                },
                "execution_times": [
                    3.99648,
                    2.01293,
                    2.20846,
                    2.5916,
                    2.00467,
                    1.84031,
                    1.85367,
                    1.8434,
                    1.85866,
                    1.84165,
                    1.88514,
                    1.84236,
                    1.87695,
                    1.84399,
                    1.84954,
                    1.83749,
                    1.83857,
                    1.83691,
                    1.84111,
                    1.85213,
                    1.83841,
                    1.85001,
                    1.839,
                    1.86335,
                    1.84077,
                    1.848,
                    1.83919,
                    1.84777,
                    1.8413,
                    1.84928
                ],
                "legality_check": true,
                "exploration_method": 1,
                "sched_str": "{comp00}:"
            },
            {
                "comp00": {
                    "tiling": {},
                    "unrolling_factor": null,
                    "parallelized_dim": null,
                    "shiftings": null,
                    "transformations_list": [
                        [
                            1,
                            0,
                            1,
                            0,
                            0,
                            0,
                            0,
                            0,
                            0,
                            0,
                            0,
                            0,
                            0,
                            0,
                            0,
                            0
                        ]
                    ]
                },
                "unfuse_iterators": [],
                "tree_structure": {
                    "roots": [
                        {
                            "loop_name": "i0",
                            "computations_list": [],
                            "child_list": [
                                {
                                    "loop_name": "i1",
                                    "computations_list": [],
                                    "child_list": [
                                        {
                                            "loop_name": "i2",
                                            "computations_list": [
                                                "comp00"
                                            ],
                                            "child_list": []
                                        }
                                    ]
                                }
                            ]
                        }
                    ]
                },
                "execution_times": [
                    3.47085,
                    1.60624,
                    1.56135,
                    1.55548,
                    1.55168,
                    1.5765,
                    1.562,
                    1.58326,
                    1.56733,
                    1.55883,
                    1.58348,
                    1.56221,
                    1.5724,
                    1.57957,
                    1.55878,
                    1.56782,
                    1.55832,
                    1.55447,
                    1.5919,
                    1.55769,
                    1.57848,
                    1.55719,
                    1.5533,
                    1.56655,
                    1.55621,
                    1.56537,
                    1.55693,
                    1.55438,
                    1.56242,
                    1.55264
                ],
                "legality_check": true,
                "exploration_method": 1,
                "sched_str": "{comp00}:I(L0,L1)"
            },
            {
                "comp00": {
                    "tiling": {},
                    "unrolling_factor": null,
                    "parallelized_dim": null,
                    "shiftings": null,
                    "transformations_list": [
                        [
                            1,
                            0,
                            2,
                            0,
                            0,
                            0,
                            0,
                            0,
                            0,
                            0,
                            0,
                            0,
                            0,
                            0,
                            0,
                            0
                        ]
                    ]
                },
                "unfuse_iterators": [],
                "tree_structure": {
                    "roots": [
                        {
                            "loop_name": "i0",
                            "computations_list": [],
                            "child_list": [
                                {
                                    "loop_name": "i1",
                                    "computations_list": [],
                                    "child_list": [
                                        {
                                            "loop_name": "i2",
                                            "computations_list": [
                                                "comp00"
                                            ],
                                            "child_list": []
                                        }
                                    ]
                                }
                            ]
                        }
                    ]
                },
                "execution_times": [
                    21.002899,
                    18.385099,
                    18.0886,
                    18.0662,
                    18.0853,
                    18.1005,
                    18.091499,
                    18.145599,
                    18.0945,
                    18.092501,
                    18.153999,
                    18.1063,
                    18.103201,
                    18.100401,
                    18.082199,
                    18.0875,
                    18.125,
                    18.0952,
                    18.1085,
                    18.0965,
                    18.090599,
                    18.079,
                    18.079599,
                    18.0847,
                    18.1063,
                    18.077101,
                    18.091101,
                    18.084499,
                    18.0884,
                    18.126499
                ],
                "legality_check": true,
                "exploration_method": 1,
                "sched_str": "{comp00}:I(L0,L2)"
            },
            {
                "comp00": {
                    "tiling": {},
                    "unrolling_factor": null,
                    "parallelized_dim": null,
                    "shiftings": null,
                    "transformations_list": [
                        [
                            1,
                            1,
                            2,
                            0,
                            0,
                            0,
                            0,
                            0,
                            0,
                            0,
                            0,
                            0,
                            0,
                            0,
                            0,
                            0
                        ]
                    ]
                },
                "unfuse_iterators": [],
                "tree_structure": {
                    "roots": [
                        {
                            "loop_name": "i0",
                            "computations_list": [],
                            "child_list": [
                                {
                                    "loop_name": "i1",
                                    "computations_list": [],
                                    "child_list": [
                                        {
                                            "loop_name": "i2",
                                            "computations_list": [
                                                "comp00"
                                            ],
                                            "child_list": []
                                        }
                                    ]
                                }
                            ]
                        }
                    ]
                },
                "execution_times": [
                    2.64651,
                    1.39461,
                    1.57808,
                    1.68235,
                    1.67288,
                    1.25817,
                    1.25435,
                    1.30591,
                    1.28148,
                    1.25726,
                    1.29969,
                    1.29448,
                    1.25605,
                    1.25584,
                    1.36276,
                    1.25262,
                    1.25072,
                    1.31071,
                    1.24946,
                    1.2501,
                    1.3242,
                    1.24706,
                    1.24957,
                    1.33933,
                    1.24818,
                    1.24937,
                    1.32258,
                    1.25175,
                    1.25202,
                    1.25479
                ],
                "legality_check": true,
                "exploration_method": 1,
                "sched_str": "{comp00}:I(L1,L2)"
            },
            {
                "comp00": {
                    "tiling": {},
                    "unrolling_factor": null,
                    "parallelized_dim": "i0",
                    "shiftings": null,
                    "transformations_list": [
                        [
                            1,
                            1,
                            2,
                            0,
                            0,
                            0,
                            0,
                            0,
                            0,
                            0,
                            0,
                            0,
                            0,
                            0,
                            0,
                            0
                        ]
                    ]
                },
                "unfuse_iterators": [],
                "tree_structure": {
                    "roots": [
                        {
                            "loop_name": "i0",
                            "computations_list": [],
                            "child_list": [
                                {
                                    "loop_name": "i1",
                                    "computations_list": [],
                                    "child_list": [
                                        {
                                            "loop_name": "i2",
                                            "computations_list": [
                                                "comp00"
                                            ],
                                            "child_list": []
                                        }
                                    ]
                                }
                            ]
                        }
                    ]
                },
                "execution_times": [
                    1.8703,
                    0.665925,
                    0.650687,
                    0.62467,
                    0.622892,
                    0.58883,
                    0.622658,
                    0.628119,
                    0.632171,
                    0.599022,
                    0.603432,
                    0.572284,
                    0.557981,
                    0.556481,
                    0.569809,
                    0.555705,
                    0.557752,
                    0.559366,
                    0.583508,
                    0.559664,
                    0.528975,
                    0.537934,
                    0.543299,
                    0.560589,
                    0.552553,
                    0.572896,
                    0.548642,
                    0.573289,
                    0.571516,
                    0.546205
                ],
                "legality_check": true,
                "exploration_method": 1,
                "sched_str": "{comp00}:I(L1,L2)P(L0)"
            },
            {
                "comp00": {
                    "tiling": {},
                    "unrolling_factor": null,
                    "parallelized_dim": "i2",
                    "shiftings": null,
                    "transformations_list": [
                        [
                            1,
                            1,
                            2,
                            0,
                            0,
                            0,
                            0,
                            0,
                            0,
                            0,
                            0,
                            0,
                            0,
                            0,
                            0,
                            0
                        ]
                    ]
                },
                "unfuse_iterators": [],
                "tree_structure": {
                    "roots": [
                        {
                            "loop_name": "i0",
                            "computations_list": [],
                            "child_list": [
                                {
                                    "loop_name": "i1",
                                    "computations_list": [],
                                    "child_list": [
                                        {
                                            "loop_name": "i2",
                                            "computations_list": [
                                                "comp00"
                                            ],
                                            "child_list": []
                                        }
                                    ]
                                }
                            ]
                        }
                    ]
                },
                "execution_times": [
                    146.013,
                    146.201004,
                    144.876999,
                    144.242004,
                    144.602997,
                    144.080002,
                    145.778,
                    147.649002,
                    146.623001,
                    144.712006,
                    143.013,
                    141.807007,
                    142.095001,
                    141.942001,
                    142.251007,
                    141.617004,
                    143.153,
                    149.345001,
                    156.488998,
                    141.761993,
                    141.270004,
                    141.966003,
                    141.442001,
                    142.136993,
                    141.565994,
                    142.044006,
                    141.485001,
                    141.475006,
                    141.203003,
                    140.992004
                ],
                "legality_check": true,
                "exploration_method": 1,
                "sched_str": "{comp00}:I(L1,L2)P(L2)"
            },
            {
                "comp00": {
                    "tiling": {
                        "tiling_depth": 2,
                        "tiling_dims": [
                            "i0",
                            "i2"
                        ],
                        "tiling_factors": [
                            32,
                            32
                        ]
                    },
                    "unrolling_factor": null,
                    "parallelized_dim": null,
                    "shiftings": null,
                    "transformations_list": [
                        [
                            1,
                            1,
                            2,
                            0,
                            0,
                            0,
                            0,
                            0,
                            0,
                            0,
                            0,
                            0,
                            0,
                            0,
                            0,
                            0
                        ]
                    ]
                },
                "unfuse_iterators": [],
                "tree_structure": {
                    "roots": [
                        {
                            "loop_name": "i0",
                            "computations_list": [],
                            "child_list": [
                                {
                                    "loop_name": "i1",
                                    "computations_list": [],
                                    "child_list": [
                                        {
                                            "loop_name": "i2",
                                            "computations_list": [
                                                "comp00"
                                            ],
                                            "child_list": []
                                        }
                                    ]
                                }
                            ]
                        }
                    ]
                },
                "execution_times": [
                    4.64947,
                    2.08845,
                    2.09512,
                    2.078,
                    2.09823,
                    2.09074,
                    2.10729,
                    2.0878,
                    2.07881,
                    2.12122,
                    2.08466,
                    2.0886,
                    2.08044,
                    2.08696,
                    2.08443,
                    2.08439,
                    2.08077,
                    2.08169,
                    2.07461,
                    2.08507,
                    2.07595,
                    2.08782,
                    2.07619,
                    2.08051,
                    2.07669,
                    2.08893,
                    2.08211,
                    2.08485,
                    2.08782,
                    2.08134
                ],
                "legality_check": true,
                "exploration_method": 1,
                "sched_str": "{comp00}:I(L1,L2)T2(L0,L2,32,32)"
            },
            {
                "comp00": {
                    "tiling": {
                        "tiling_depth": 2,
                        "tiling_dims": [
                            "i0",
                            "i2"
                        ],
                        "tiling_factors": [
                            32,
                            64
                        ]
                    },
                    "unrolling_factor": null,
                    "parallelized_dim": null,
                    "shiftings": null,
                    "transformations_list": [
                        [
                            1,
                            1,
                            2,
                            0,
                            0,
                            0,
                            0,
                            0,
                            0,
                            0,
                            0,
                            0,
                            0,
                            0,
                            0,
                            0
                        ]
                    ]
                },
                "unfuse_iterators": [],
                "tree_structure": {
                    "roots": [
                        {
                            "loop_name": "i0",
                            "computations_list": [],
                            "child_list": [
                                {
                                    "loop_name": "i1",
                                    "computations_list": [],
                                    "child_list": [
                                        {
                                            "loop_name": "i2",
                                            "computations_list": [
                                                "comp00"
                                            ],
                                            "child_list": []
                                        }
                                    ]
                                }
                            ]
                        }
                    ]
                },
                "execution_times": [
                    3.37256,
                    1.60419,
                    1.79788,
                    2.11407,
                    1.84613,
                    1.43394,
                    1.42946,
                    1.49391,
                    1.43053,
                    1.4536,
                    1.45968,
                    1.4298,
                    1.54496,
                    1.43657,
                    1.43074,
                    1.53014,
                    1.43265,
                    1.42753,
                    1.43225,
                    1.42848,
                    1.45033,
                    1.45314,
                    1.43301,
                    1.43517,
                    1.43262,
                    1.4311,
                    1.43197,
                    1.43138,
                    1.42588,
                    1.43689
                ],
                "legality_check": true,
                "exploration_method": 1,
                "sched_str": "{comp00}:I(L1,L2)T2(L0,L2,32,64)"
            },
            {
                "comp00": {
                    "tiling": {
                        "tiling_depth": 2,
                        "tiling_dims": [
                            "i0",
                            "i2"
                        ],
                        "tiling_factors": [
                            32,
                            128
                        ]
                    },
                    "unrolling_factor": null,
                    "parallelized_dim": null,
                    "shiftings": null,
                    "transformations_list": [
                        [
                            1,
                            1,
                            2,
                            0,
                            0,
                            0,
                            0,
                            0,
                            0,
                            0,
                            0,
                            0,
                            0,
                            0,
                            0,
                            0
                        ]
                    ]
                },
                "unfuse_iterators": [],
                "tree_structure": {
                    "roots": [
                        {
                            "loop_name": "i0",
                            "computations_list": [],
                            "child_list": [
                                {
                                    "loop_name": "i1",
                                    "computations_list": [],
                                    "child_list": [
                                        {
                                            "loop_name": "i2",
                                            "computations_list": [
                                                "comp00"
                                            ],
                                            "child_list": []
                                        }
                                    ]
                                }
                            ]
                        }
                    ]
                },
                "execution_times": [
                    3.1057,
                    1.50805,
                    1.48722,
                    1.5507,
                    1.40391,
                    1.38688,
                    1.44319,
                    1.34821,
                    1.34422,
                    1.4488,
                    1.34582,
                    1.34219,
                    1.43231,
                    1.34485,
                    1.34253,
                    1.43923,
                    1.34533,
                    1.38589,
                    1.48404,
                    1.34683,
                    1.34386,
                    1.40218,
                    1.3475,
                    1.34437,
                    1.40364,
                    1.34406,
                    1.36834,
                    1.3615,
                    1.34702,
                    1.34568
                ],
                "legality_check": true,
                "exploration_method": 1,
                "sched_str": "{comp00}:I(L1,L2)T2(L0,L2,32,128)"
            },
            {
                "comp00": {
                    "tiling": {
                        "tiling_depth": 2,
                        "tiling_dims": [
                            "i0",
                            "i2"
                        ],
                        "tiling_factors": [
                            64,
                            32
                        ]
                    },
                    "unrolling_factor": null,
                    "parallelized_dim": null,
                    "shiftings": null,
                    "transformations_list": [
                        [
                            1,
                            1,
                            2,
                            0,
                            0,
                            0,
                            0,
                            0,
                            0,
                            0,
                            0,
                            0,
                            0,
                            0,
                            0,
                            0
                        ]
                    ]
                },
                "unfuse_iterators": [],
                "tree_structure": {
                    "roots": [
                        {
                            "loop_name": "i0",
                            "computations_list": [],
                            "child_list": [
                                {
                                    "loop_name": "i1",
                                    "computations_list": [],
                                    "child_list": [
                                        {
                                            "loop_name": "i2",
                                            "computations_list": [
                                                "comp00"
                                            ],
                                            "child_list": []
                                        }
                                    ]
                                }
                            ]
                        }
                    ]
                },
                "execution_times": [
                    3.99312,
                    1.78686,
                    1.77564,
                    1.79589,
                    1.78597,
                    1.70256,
                    1.59853,
                    1.68604,
                    1.59908,
                    1.59946,
                    1.67791,
                    1.59929,
                    1.70809,
                    1.60532,
                    1.59507,
                    1.68501,
                    1.6069,
                    1.70322,
                    1.59757,
                    1.65584,
                    1.63484,
                    1.60182,
                    1.62269,
                    1.59428,
                    1.61023,
                    1.59419,
                    1.60094,
                    1.60227,
                    1.59864,
                    1.61489
                ],
                "legality_check": true,
                "exploration_method": 1,
                "sched_str": "{comp00}:I(L1,L2)T2(L0,L2,64,32)"
            },
            {
                "comp00": {
                    "tiling": {
                        "tiling_depth": 2,
                        "tiling_dims": [
                            "i0",
                            "i2"
                        ],
                        "tiling_factors": [
                            64,
                            64
                        ]
                    },
                    "unrolling_factor": null,
                    "parallelized_dim": null,
                    "shiftings": null,
                    "transformations_list": [
                        [
                            1,
                            1,
                            2,
                            0,
                            0,
                            0,
                            0,
                            0,
                            0,
                            0,
                            0,
                            0,
                            0,
                            0,
                            0,
                            0
                        ]
                    ]
                },
                "unfuse_iterators": [],
                "tree_structure": {
                    "roots": [
                        {
                            "loop_name": "i0",
                            "computations_list": [],
                            "child_list": [
                                {
                                    "loop_name": "i1",
                                    "computations_list": [],
                                    "child_list": [
                                        {
                                            "loop_name": "i2",
                                            "computations_list": [
                                                "comp00"
                                            ],
                                            "child_list": []
                                        }
                                    ]
                                }
                            ]
                        }
                    ]
                },
                "execution_times": [
                    3.84009,
                    1.91883,
                    1.89076,
                    1.90264,
                    1.91185,
                    1.89157,
                    1.92762,
                    1.88988,
                    1.92178,
                    1.8964,
                    1.91015,
                    1.89156,
                    1.90107,
                    1.89543,
                    1.90581,
                    1.89723,
                    1.89071,
                    1.88974,
                    1.93866,
                    1.89963,
                    1.89923,
                    1.89214,
                    1.89887,
                    1.88202,
                    1.89848,
                    1.88958,
                    1.88694,
                    1.88925,
                    1.89132,
                    1.90277
                ],
                "legality_check": true,
                "exploration_method": 1,
                "sched_str": "{comp00}:I(L1,L2)T2(L0,L2,64,64)"
            },
            {
                "comp00": {
                    "tiling": {
                        "tiling_depth": 2,
                        "tiling_dims": [
                            "i0",
                            "i2"
                        ],
                        "tiling_factors": [
                            64,
                            128
                        ]
                    },
                    "unrolling_factor": null,
                    "parallelized_dim": null,
                    "shiftings": null,
                    "transformations_list": [
                        [
                            1,
                            1,
                            2,
                            0,
                            0,
                            0,
                            0,
                            0,
                            0,
                            0,
                            0,
                            0,
                            0,
                            0,
                            0,
                            0
                        ]
                    ]
                },
                "unfuse_iterators": [],
                "tree_structure": {
                    "roots": [
                        {
                            "loop_name": "i0",
                            "computations_list": [],
                            "child_list": [
                                {
                                    "loop_name": "i1",
                                    "computations_list": [],
                                    "child_list": [
                                        {
                                            "loop_name": "i2",
                                            "computations_list": [
                                                "comp00"
                                            ],
                                            "child_list": []
                                        }
                                    ]
                                }
                            ]
                        }
                    ]
                },
                "execution_times": [
                    2.91401,
                    1.46095,
                    1.456,
                    1.46244,
                    1.45394,
                    1.45585,
                    1.40642,
                    1.30866,
                    1.30584,
                    1.36945,
                    1.30991,
                    1.31017,
                    1.36308,
                    1.30908,
                    1.30702,
                    1.36655,
                    1.30806,
                    1.30546,
                    1.4053,
                    1.31161,
                    1.30814,
                    1.37017,
                    1.30856,
                    1.30797,
                    1.37752,
                    1.31038,
                    1.30902,
                    1.36879,
                    1.30838,
                    1.30512
                ],
                "legality_check": true,
                "exploration_method": 1,
                "sched_str": "{comp00}:I(L1,L2)T2(L0,L2,64,128)"
            },
            {
                "comp00": {
                    "tiling": {
                        "tiling_depth": 2,
                        "tiling_dims": [
                            "i0",
                            "i2"
                        ],
                        "tiling_factors": [
                            128,
                            32
                        ]
                    },
                    "unrolling_factor": null,
                    "parallelized_dim": null,
                    "shiftings": null,
                    "transformations_list": [
                        [
                            1,
                            1,
                            2,
                            0,
                            0,
                            0,
                            0,
                            0,
                            0,
                            0,
                            0,
                            0,
                            0,
                            0,
                            0,
                            0
                        ]
                    ]
                },
                "unfuse_iterators": [],
                "tree_structure": {
                    "roots": [
                        {
                            "loop_name": "i0",
                            "computations_list": [],
                            "child_list": [
                                {
                                    "loop_name": "i1",
                                    "computations_list": [],
                                    "child_list": [
                                        {
                                            "loop_name": "i2",
                                            "computations_list": [
                                                "comp00"
                                            ],
                                            "child_list": []
                                        }
                                    ]
                                }
                            ]
                        }
                    ]
                },
                "execution_times": [
                    4.30843,
                    2.16948,
                    2.15496,
                    2.17867,
                    2.17907,
                    2.16222,
                    2.18287,
                    2.16526,
                    2.16673,
                    2.15772,
                    2.19154,
                    2.16221,
                    2.20892,
                    2.1659,
                    2.16813,
                    2.16547,
                    2.16078,
                    2.16058,
                    2.15909,
                    2.16687,
                    2.15921,
                    2.16241,
                    2.15499,
                    2.1622,
                    2.1576,
                    2.16341,
                    2.16698,
                    2.15787,
                    2.16393,
                    2.15444
                ],
                "legality_check": true,
                "exploration_method": 1,
                "sched_str": "{comp00}:I(L1,L2)T2(L0,L2,128,32)"
            },
            {
                "comp00": {
                    "tiling": {
                        "tiling_depth": 2,
                        "tiling_dims": [
                            "i0",
                            "i2"
                        ],
                        "tiling_factors": [
                            128,
                            64
                        ]
                    },
                    "unrolling_factor": null,
                    "parallelized_dim": null,
                    "shiftings": null,
                    "transformations_list": [
                        [
                            1,
                            1,
                            2,
                            0,
                            0,
                            0,
                            0,
                            0,
                            0,
                            0,
                            0,
                            0,
                            0,
                            0,
                            0,
                            0
                        ]
                    ]
                },
                "unfuse_iterators": [],
                "tree_structure": {
                    "roots": [
                        {
                            "loop_name": "i0",
                            "computations_list": [],
                            "child_list": [
                                {
                                    "loop_name": "i1",
                                    "computations_list": [],
                                    "child_list": [
                                        {
                                            "loop_name": "i2",
                                            "computations_list": [
                                                "comp00"
                                            ],
                                            "child_list": []
                                        }
                                    ]
                                }
                            ]
                        }
                    ]
                },
                "execution_times": [
                    3.50215,
                    1.65366,
                    1.63622,
                    1.68921,
                    1.63574,
                    1.63836,
                    1.4811,
                    1.47426,
                    1.55275,
                    1.47705,
                    1.51668,
                    1.50084,
                    1.47527,
                    1.59929,
                    1.48327,
                    1.47282,
                    1.55042,
                    1.47838,
                    1.54369,
                    1.48168,
                    1.4709,
                    1.559,
                    1.4759,
                    1.47346,
                    1.53312,
                    1.47699,
                    1.47868,
                    1.47212,
                    1.47253,
                    1.48605
                ],
                "legality_check": true,
                "exploration_method": 1,
                "sched_str": "{comp00}:I(L1,L2)T2(L0,L2,128,64)"
            },
            {
                "comp00": {
                    "tiling": {
                        "tiling_depth": 2,
                        "tiling_dims": [
                            "i0",
                            "i2"
                        ],
                        "tiling_factors": [
                            128,
                            128
                        ]
                    },
                    "unrolling_factor": null,
                    "parallelized_dim": null,
                    "shiftings": null,
                    "transformations_list": [
                        [
                            1,
                            1,
                            2,
                            0,
                            0,
                            0,
                            0,
                            0,
                            0,
                            0,
                            0,
                            0,
                            0,
                            0,
                            0,
                            0
                        ]
                    ]
                },
                "unfuse_iterators": [],
                "tree_structure": {
                    "roots": [
                        {
                            "loop_name": "i0",
                            "computations_list": [],
                            "child_list": [
                                {
                                    "loop_name": "i1",
                                    "computations_list": [],
                                    "child_list": [
                                        {
                                            "loop_name": "i2",
                                            "computations_list": [
                                                "comp00"
                                            ],
                                            "child_list": []
                                        }
                                    ]
                                }
                            ]
                        }
                    ]
                },
                "execution_times": [
                    3.50015,
                    1.8889,
                    1.83388,
                    1.72723,
                    1.7419,
                    1.74329,
                    1.74239,
                    1.74133,
                    1.72824,
                    1.75772,
                    1.73253,
                    1.78331,
                    1.72985,
                    1.75119,
                    1.72848,
                    1.72539,
                    1.73914,
                    1.7315,
                    1.7331,
                    1.73119,
                    1.73863,
                    1.73292,
                    1.73378,
                    1.72528,
                    1.73049,
                    1.73809,
                    1.72858,
                    1.73485,
                    1.72744,
                    1.73316
                ],
                "legality_check": true,
                "exploration_method": 1,
                "sched_str": "{comp00}:I(L1,L2)T2(L0,L2,128,128)"
            },
            {
                "comp00": {
                    "tiling": {
                        "tiling_depth": 2,
                        "tiling_dims": [
                            "i0",
                            "i2"
                        ],
                        "tiling_factors": [
                            32,
                            128
                        ]
                    },
                    "unrolling_factor": 4,
                    "parallelized_dim": null,
                    "shiftings": null,
                    "transformations_list": [
                        [
                            1,
                            1,
                            2,
                            0,
                            0,
                            0,
                            0,
                            0,
                            0,
                            0,
                            0,
                            0,
                            0,
                            0,
                            0,
                            0
                        ]
                    ]
                },
                "unfuse_iterators": [],
                "tree_structure": {
                    "roots": [
                        {
                            "loop_name": "i0",
                            "computations_list": [],
                            "child_list": [
                                {
                                    "loop_name": "i1",
                                    "computations_list": [],
                                    "child_list": [
                                        {
                                            "loop_name": "i2",
                                            "computations_list": [
                                                "comp00"
                                            ],
                                            "child_list": []
                                        }
                                    ]
                                }
                            ]
                        }
                    ]
                },
                "execution_times": [
                    3.50385,
                    1.73547,
                    1.74172,
                    1.72248,
                    1.73994,
                    1.72479,
                    1.74894,
                    1.73043,
                    1.72327,
                    1.7486,
                    1.72907,
                    1.75842,
                    1.72515,
                    1.73261,
                    1.72196,
                    1.72593,
                    1.72888,
                    1.72461,
                    1.76353,
                    1.72715,
                    1.72881,
                    1.72271,
                    1.73097,
                    1.72187,
                    1.72209,
                    1.72894,
                    1.72169,
                    1.72645,
                    1.72714,
                    1.72746
                ],
                "legality_check": true,
                "exploration_method": 1,
                "sched_str": "{comp00}:I(L1,L2)T2(L0,L2,32,128)U(L4,4)"
            },
            {
                "comp00": {
                    "tiling": {
                        "tiling_depth": 2,
                        "tiling_dims": [
                            "i0",
                            "i2"
                        ],
                        "tiling_factors": [
                            32,
                            128
                        ]
                    },
                    "unrolling_factor": 8,
                    "parallelized_dim": null,
                    "shiftings": null,
                    "transformations_list": [
                        [
                            1,
                            1,
                            2,
                            0,
                            0,
                            0,
                            0,
                            0,
                            0,
                            0,
                            0,
                            0,
                            0,
                            0,
                            0,
                            0
                        ]
                    ]
                },
                "unfuse_iterators": [],
                "tree_structure": {
                    "roots": [
                        {
                            "loop_name": "i0",
                            "computations_list": [],
                            "child_list": [
                                {
                                    "loop_name": "i1",
                                    "computations_list": [],
                                    "child_list": [
                                        {
                                            "loop_name": "i2",
                                            "computations_list": [
                                                "comp00"
                                            ],
                                            "child_list": []
                                        }
                                    ]
                                }
                            ]
                        }
                    ]
                },
                "execution_times": [
                    2.9909,
                    1.60104,
                    1.58394,
                    1.57198,
                    1.47274,
                    1.47363,
                    1.40802,
                    1.3295,
                    1.32652,
                    1.41875,
                    1.32526,
                    1.32787,
                    1.37771,
                    1.32759,
                    1.32839,
                    1.40508,
                    1.326,
                    1.36147,
                    1.35135,
                    1.32959,
                    1.33087,
                    1.32902,
                    1.324,
                    1.34848,
                    1.34208,
                    1.3205,
                    1.33091,
                    1.32672,
                    1.32645,
                    1.3287
                ],
                "legality_check": true,
                "exploration_method": 1,
                "sched_str": "{comp00}:I(L1,L2)T2(L0,L2,32,128)U(L4,8)"
            },
            {
                "comp00": {
                    "tiling": {
                        "tiling_depth": 2,
                        "tiling_dims": [
                            "i0",
                            "i2"
                        ],
                        "tiling_factors": [
                            128,
                            64
                        ]
                    },
                    "unrolling_factor": 4,
                    "parallelized_dim": null,
                    "shiftings": null,
                    "transformations_list": [
                        [
                            1,
                            1,
                            2,
                            0,
                            0,
                            0,
                            0,
                            0,
                            0,
                            0,
                            0,
                            0,
                            0,
                            0,
                            0,
                            0
                        ]
                    ]
                },
                "unfuse_iterators": [],
                "tree_structure": {
                    "roots": [
                        {
                            "loop_name": "i0",
                            "computations_list": [],
                            "child_list": [
                                {
                                    "loop_name": "i1",
                                    "computations_list": [],
                                    "child_list": [
                                        {
                                            "loop_name": "i2",
                                            "computations_list": [
                                                "comp00"
                                            ],
                                            "child_list": []
                                        }
                                    ]
                                }
                            ]
                        }
                    ]
                },
                "execution_times": [
                    3.41854,
                    1.66434,
                    1.9832,
                    1.989,
                    1.48149,
                    1.47067,
                    1.55918,
                    1.46368,
                    1.46436,
                    1.54669,
                    1.45826,
                    1.50606,
                    1.49868,
                    1.46843,
                    1.57844,
                    1.46668,
                    1.46701,
                    1.52746,
                    1.46643,
                    1.50099,
                    1.46813,
                    1.46768,
                    1.50745,
                    1.46333,
                    1.46435,
                    1.4677,
                    1.4633,
                    1.4643,
                    1.46442,
                    1.46399
                ],
                "legality_check": true,
                "exploration_method": 1,
                "sched_str": "{comp00}:I(L1,L2)T2(L0,L2,128,64)U(L4,4)"
            },
            {
                "comp00": {
                    "tiling": {
                        "tiling_depth": 2,
                        "tiling_dims": [
                            "i0",
                            "i2"
                        ],
                        "tiling_factors": [
                            128,
                            64
                        ]
                    },
                    "unrolling_factor": 8,
                    "parallelized_dim": null,
                    "shiftings": null,
                    "transformations_list": [
                        [
                            1,
                            1,
                            2,
                            0,
                            0,
                            0,
                            0,
                            0,
                            0,
                            0,
                            0,
                            0,
                            0,
                            0,
                            0,
                            0
                        ]
                    ]
                },
                "unfuse_iterators": [],
                "tree_structure": {
                    "roots": [
                        {
                            "loop_name": "i0",
                            "computations_list": [],
                            "child_list": [
                                {
                                    "loop_name": "i1",
                                    "computations_list": [],
                                    "child_list": [
                                        {
                                            "loop_name": "i2",
                                            "computations_list": [
                                                "comp00"
                                            ],
                                            "child_list": []
                                        }
                                    ]
                                }
                            ]
                        }
                    ]
                },
                "execution_times": [
                    3.56441,
                    1.65121,
                    1.65074,
                    1.63726,
                    1.63809,
                    1.53101,
                    1.55337,
                    1.56641,
                    1.52937,
                    1.57561,
                    1.4763,
                    1.47211,
                    1.53161,
                    1.47156,
                    1.52956,
                    1.48103,
                    1.47239,
                    1.57939,
                    1.47505,
                    1.47163,
                    1.54251,
                    1.47707,
                    1.48215,
                    1.47663,
                    1.4755,
                    1.48091,
                    1.48023,
                    1.47605,
                    1.48536,
                    1.47531
                ],
                "legality_check": true,
                "exploration_method": 1,
                "sched_str": "{comp00}:I(L1,L2)T2(L0,L2,128,64)U(L4,8)"
            },
            {
                "comp00": {
                    "tiling": {},
                    "unrolling_factor": null,
                    "parallelized_dim": "i0",
                    "shiftings": null,
                    "transformations_list": []
                },
                "unfuse_iterators": [],
                "tree_structure": {
                    "roots": [
                        {
                            "loop_name": "i0",
                            "computations_list": [],
                            "child_list": [
                                {
                                    "loop_name": "i1",
                                    "computations_list": [],
                                    "child_list": [
                                        {
                                            "loop_name": "i2",
                                            "computations_list": [
                                                "comp00"
                                            ],
                                            "child_list": []
                                        }
                                    ]
                                }
                            ]
                        }
                    ]
                },
                "execution_times": [
                    1.83794,
                    0.728887,
                    0.697168,
                    0.688937,
                    0.703642,
                    0.702071,
                    0.628126,
                    0.630752,
                    0.632878,
                    0.596913,
                    0.57722,
                    0.619324,
                    0.63815,
                    0.582161,
                    0.610228,
                    0.556146,
                    0.548141,
                    0.51646,
                    0.568394,
                    0.525917,
                    0.545308,
                    0.541116,
                    0.519217,
                    0.523275,
                    0.546688,
                    0.550254,
                    0.543228,
                    0.522223,
                    0.542853,
                    0.526784
                ],
                "legality_check": true,
                "exploration_method": 1,
                "sched_str": "{comp00}:P(L0)"
            },
            {
                "comp00": {
                    "tiling": {},
                    "unrolling_factor": null,
                    "parallelized_dim": "i1",
                    "shiftings": null,
                    "transformations_list": []
                },
                "unfuse_iterators": [],
                "tree_structure": {
                    "roots": [
                        {
                            "loop_name": "i0",
                            "computations_list": [],
                            "child_list": [
                                {
                                    "loop_name": "i1",
                                    "computations_list": [],
                                    "child_list": [
                                        {
                                            "loop_name": "i2",
                                            "computations_list": [
                                                "comp00"
                                            ],
                                            "child_list": []
                                        }
                                    ]
                                }
                            ]
                        }
                    ]
                },
                "execution_times": [
                    29.632799,
                    26.205999,
                    26.4214,
                    29.0884,
                    28.9163,
                    28.6754,
                    28.784201,
                    28.8246,
                    28.7477,
                    28.8752,
                    28.4694,
                    28.4034,
                    28.680599,
                    28.8794,
                    28.744699,
                    28.5308,
                    28.3911,
                    28.600401,
                    29.097601,
                    28.670099,
                    28.9114,
                    28.5763,
                    28.848301,
                    28.6537,
                    28.632799,
                    28.8225,
                    28.583599,
                    28.756001,
                    28.683599,
                    28.979401
                ],
                "legality_check": true,
                "exploration_method": 1,
                "sched_str": "{comp00}:P(L1)"
            },
            {
                "comp00": {
                    "tiling": {},
                    "unrolling_factor": null,
                    "parallelized_dim": "i2",
                    "shiftings": null,
                    "transformations_list": []
                },
                "unfuse_iterators": [],
                "tree_structure": {
                    "roots": [
                        {
                            "loop_name": "i0",
                            "computations_list": [],
                            "child_list": [
                                {
                                    "loop_name": "i1",
                                    "computations_list": [],
                                    "child_list": [
                                        {
                                            "loop_name": "i2",
                                            "computations_list": [
                                                "comp00"
                                            ],
                                            "child_list": []
                                        }
                                    ]
                                }
                            ]
                        }
                    ]
                },
                "execution_times": [
                    1836.910034
                ],
                "legality_check": true,
                "exploration_method": 1,
                "sched_str": "{comp00}:P(L2)"
            },
            {
                "comp00": {
                    "tiling": {},
                    "unrolling_factor": 4,
                    "parallelized_dim": null,
                    "shiftings": null,
                    "transformations_list": []
                },
                "unfuse_iterators": [],
                "tree_structure": {
                    "roots": [
                        {
                            "loop_name": "i0",
                            "computations_list": [],
                            "child_list": [
                                {
                                    "loop_name": "i1",
                                    "computations_list": [],
                                    "child_list": [
                                        {
                                            "loop_name": "i2",
                                            "computations_list": [
                                                "comp00"
                                            ],
                                            "child_list": []
                                        }
                                    ]
                                }
                            ]
                        }
                    ]
                },
                "execution_times": [
                    3.23946,
                    1.40779,
                    1.70682,
                    1.85102,
                    1.64331,
                    1.27171,
                    1.27152,
                    1.33986,
                    1.27195,
                    1.26454,
                    1.35269,
                    1.26928,
                    1.26987,
                    1.4166,
                    1.36961,
                    1.29821,
                    1.37674,
                    1.29875,
                    1.29749,
                    1.35277,
                    1.29937,
                    1.29931,
                    1.37298,
                    1.26362,
                    1.26129,
                    1.31694,
                    1.25965,
                    1.25958,
                    1.28808,
                    1.25733
                ],
                "legality_check": true,
                "exploration_method": 1,
                "sched_str": "{comp00}:U(L2,4)"
            },
            {
                "comp00": {
                    "tiling": {},
                    "unrolling_factor": 8,
                    "parallelized_dim": null,
                    "shiftings": null,
                    "transformations_list": []
                },
                "unfuse_iterators": [],
                "tree_structure": {
                    "roots": [
                        {
                            "loop_name": "i0",
                            "computations_list": [],
                            "child_list": [
                                {
                                    "loop_name": "i1",
                                    "computations_list": [],
                                    "child_list": [
                                        {
                                            "loop_name": "i2",
                                            "computations_list": [
                                                "comp00"
                                            ],
                                            "child_list": []
                                        }
                                    ]
                                }
                            ]
                        }
                    ]
                },
                "execution_times": [
                    3.46295,
                    1.58211,
                    1.56397,
                    1.57999,
                    1.56011,
                    1.55979,
                    1.41275,
                    1.40854,
                    1.48166,
                    1.41163,
                    1.40624,
                    1.49244,
                    1.41332,
                    1.42789,
                    1.43449,
                    1.4075,
                    1.47698,
                    1.40698,
                    1.40601,
                    1.47407,
                    1.40729,
                    1.40449,
                    1.50737,
                    1.40426,
                    1.40334,
                    1.44373,
                    1.40365,
                    1.41415,
                    1.40534,
                    1.40555
                ],
                "legality_check": true,
                "exploration_method": 1,
                "sched_str": "{comp00}:U(L2,8)"
            },
            {
                "comp00": {
                    "tiling": {},
                    "unrolling_factor": 16,
                    "parallelized_dim": null,
                    "shiftings": null,
                    "transformations_list": []
                },
                "unfuse_iterators": [],
                "tree_structure": {
                    "roots": [
                        {
                            "loop_name": "i0",
                            "computations_list": [],
                            "child_list": [
                                {
                                    "loop_name": "i1",
                                    "computations_list": [],
                                    "child_list": [
                                        {
                                            "loop_name": "i2",
                                            "computations_list": [
                                                "comp00"
                                            ],
                                            "child_list": []
                                        }
                                    ]
                                }
                            ]
                        }
                    ]
                },
                "execution_times": [
                    3.51759,
                    1.38589,
                    1.43612,
                    1.43064,
                    1.44395,
                    1.43651,
                    1.40092,
                    1.03753,
                    1.02872,
                    1.02576,
                    1.10193,
                    1.03474,
                    1.02782,
                    1.0317,
                    1.10101,
                    1.03122,
                    1.02564,
                    1.02555,
                    1.11358,
                    1.03186,
                    1.02631,
                    1.05111,
                    1.05391,
                    1.02832,
                    1.02515,
                    1.0722,
                    1.03594,
                    1.02749,
                    1.02592,
                    1.10686
                ],
                "legality_check": true,
                "exploration_method": 1,
                "sched_str": "{comp00}:U(L2,16)"
            }
        ],
        "exploration_trace": {
            "id": 0,
            "schedule": "",
            "depth": 1,
            "evaluation": 1.83691,
            "children": [
                {
                    "id": 1,
                    "schedule": "I(L0,L1)",
                    "depth": 1,
                    "evaluation": 1.55168,
                    "children": []
                },
                {
                    "id": 2,
                    "schedule": "I(L0,L2)",
                    "depth": 1,
                    "evaluation": 18.0662,
                    "children": []
                },
                {
                    "id": 3,
                    "schedule": "I(L1,L2)",
                    "depth": 1,
                    "evaluation": 1.24706,
                    "children": [
                        {
                            "id": 4,
                            "schedule": "I(L1,L2)P(L0)",
                            "depth": 2,
                            "evaluation": 0.528975,
                            "children": []
                        },
                        {
                            "id": 5,
                            "schedule": "I(L1,L2)P(L1)",
                            "depth": 2,
                            "evaluation": 140.992004,
                            "children": []
                        },
                        {
                            "id": 6,
                            "schedule": "I(L1,L2)P(L2)",
                            "depth": 2,
                            "evaluation": 1836.910034,
                            "children": [
                                {
                                    "id": 6,
                                    "schedule": "I(L1,L2)P(L2)",
                                    "depth": 3,
                                    "evaluation": 1836.910034,
                                    "children": []
                                }
                            ]
                        },
                        {
                            "id": 3,
                            "schedule": "I(L1,L2)",
                            "depth": 2,
                            "evaluation": 1.24706,
                            "children": [
                                {
                                    "id": 7,
                                    "schedule": "I(L1,L2)T2(L0,L1,32,32)",
                                    "depth": 3,
                                    "evaluation": 2.07461,
                                    "children": []
                                },
                                {
                                    "id": 8,
                                    "schedule": "I(L1,L2)T2(L0,L1,32,64)",
                                    "depth": 3,
                                    "evaluation": 1.42588,
                                    "children": []
                                },
                                {
                                    "id": 9,
                                    "schedule": "I(L1,L2)T2(L0,L1,32,128)",
                                    "depth": 3,
                                    "evaluation": 1.34219,
                                    "children": [
                                        {
                                            "id": 16,
                                            "schedule": "I(L1,L2)T2(L0,L1,32,128)U(L4,4)",
                                            "depth": 4,
                                            "evaluation": 1.72169,
                                            "children": []
                                        },
                                        {
                                            "id": 17,
                                            "schedule": "I(L1,L2)T2(L0,L1,32,128)U(L4,8)",
                                            "depth": 4,
                                            "evaluation": 1.3205,
                                            "children": []
                                        }
                                    ]
                                },
                                {
                                    "id": 10,
                                    "schedule": "I(L1,L2)T2(L0,L1,64,32)",
                                    "depth": 3,
                                    "evaluation": 1.59419,
                                    "children": []
                                },
                                {
                                    "id": 11,
                                    "schedule": "I(L1,L2)T2(L0,L1,64,64)",
                                    "depth": 3,
                                    "evaluation": 1.88202,
                                    "children": []
                                },
                                {
                                    "id": 12,
                                    "schedule": "I(L1,L2)T2(L0,L1,64,128)",
                                    "depth": 3,
                                    "evaluation": 1.30512,
                                    "children": []
                                },
                                {
                                    "id": 13,
                                    "schedule": "I(L1,L2)T2(L0,L1,128,32)",
                                    "depth": 3,
                                    "evaluation": 2.15444,
                                    "children": []
                                },
                                {
                                    "id": 14,
                                    "schedule": "I(L1,L2)T2(L0,L1,128,64)",
                                    "depth": 3,
                                    "evaluation": 1.4709,
                                    "children": [
                                        {
                                            "id": 18,
                                            "schedule": "I(L1,L2)T2(L0,L1,128,64)U(L4,4)",
                                            "depth": 4,
                                            "evaluation": 1.45826,
                                            "children": []
                                        },
                                        {
                                            "id": 19,
                                            "schedule": "I(L1,L2)T2(L0,L1,128,64)U(L4,8)",
                                            "depth": 4,
                                            "evaluation": 1.47156,
                                            "children": []
                                        }
                                    ]
                                },
                                {
                                    "id": 15,
                                    "schedule": "I(L1,L2)T2(L0,L1,128,128)",
                                    "depth": 3,
                                    "evaluation": 1.72528,
                                    "children": []
                                },
                                {
                                    "id": 3,
                                    "schedule": "I(L1,L2)",
                                    "depth": 3,
                                    "evaluation": 1.24706,
                                    "children": []
                                }
                            ]
                        }
                    ]
                },
                {
                    "id": 0,
                    "schedule": "",
                    "depth": 1,
                    "evaluation": 1.83691,
                    "children": [
                        {
                            "id": 20,
                            "schedule": "P(L0)",
                            "depth": 2,
                            "evaluation": 0.51646,
                            "children": []
                        },
                        {
                            "id": 21,
                            "schedule": "P(L1)",
                            "depth": 2,
                            "evaluation": 26.205999,
                            "children": []
                        },
                        {
                            "id": 22,
                            "schedule": "P(L2)",
                            "depth": 2,
                            "evaluation": 1836.910034,
                            "children": []
                        },
                        {
                            "id": 0,
                            "schedule": "",
                            "depth": 2,
                            "evaluation": 1.83691,
                            "children": [
                                {
                                    "id": 23,
                                    "schedule": "U(L2,4)",
                                    "depth": 3,
                                    "evaluation": 1.25733,
                                    "children": []
                                },
                                {
                                    "id": 24,
                                    "schedule": "U(L2,8)",
                                    "depth": 3,
                                    "evaluation": 1.40334,
                                    "children": []
                                },
                                {
                                    "id": 25,
                                    "schedule": "U(L2,16)",
                                    "depth": 3,
                                    "evaluation": 1.02515,
                                    "children": []
                                }
                            ]
                        }
                    ]
                }
            ]
        }
    }
}