{
    "function1176890": {
        "filename": "./function1176890_explored_schedules.json",
        "node_name": "lanka16",
        "parameters": {
            "beam_size": 3,
            "max_depth": 3
        },
        "program_annotation": {
            "memory_size": 0.00206756591796875,
            "iterators": {
                "i0": {
                    "lower_bound": 1,
                    "upper_bound": 65,
                    "parent_iterator": null,
                    "child_iterators": [
                        "i1"
                    ],
                    "computations_list": []
                },
                "i1": {
                    "lower_bound": 1,
                    "upper_bound": 7,
                    "parent_iterator": "i0",
                    "child_iterators": [
                        "i2"
                    ],
                    "computations_list": [
                        "comp00"
                    ]
                },
                "i2": {
                    "lower_bound": "i1",
                    "upper_bound": 9,
                    "parent_iterator": "i1",
                    "child_iterators": [],
                    "computations_list": [
                        "comp01"
                    ]
                }
            },
            "computations": {
                "comp00": {
                    "absolute_order": 1,
                    "iterators": [
                        "i0",
                        "i1"
                    ],
                    "comp_is_reduction": true,
                    "write_access_relation": "{ comp00[i0, i1] -> buf00[i1] }",
                    "write_buffer_id": 0,
                    "data_type": "int32",
                    "data_type_size": 0,
                    "accesses": [
                        {
                            "access_is_reduction": true,
                            "buffer_id": 0,
                            "access_matrix": [
                                [
                                    0,
                                    1,
                                    0
                                ]
                            ]
                        },
                        {
                            "access_is_reduction": false,
                            "buffer_id": 1,
                            "access_matrix": [
                                [
                                    0,
                                    1,
                                    0
                                ]
                            ]
                        },
                        {
                            "access_is_reduction": true,
                            "buffer_id": 0,
                            "access_matrix": [
                                [
                                    0,
                                    1,
                                    0
                                ]
                            ]
                        }
                    ],
                    "expression_representation": {
                        "expr_type": "add",
                        "children": [
                            {
                                "expr_type": "add",
                                "children": [
                                    {
                                        "expr_type": "mul",
                                        "children": [
                                            {
                                                "expr_type": "mul",
                                                "children": [
                                                    {
                                                        "expr_type": "value",
                                                        "children": []
                                                    },
                                                    {
                                                        "expr_type": "access",
                                                        "children": []
                                                    }
                                                ]
                                            },
                                            {
                                                "expr_type": "access",
                                                "children": []
                                            }
                                        ]
                                    },
                                    {
                                        "expr_type": "mul",
                                        "children": [
                                            {
                                                "expr_type": "value",
                                                "children": []
                                            },
                                            {
                                                "expr_type": "access",
                                                "children": []
                                            }
                                        ]
                                    }
                                ]
                            },
                            {
                                "expr_type": "value",
                                "children": []
                            }
                        ]
                    }
                },
                "comp01": {
                    "absolute_order": 2,
                    "iterators": [
                        "i0",
                        "i1",
                        "i2"
                    ],
                    "comp_is_reduction": true,
                    "write_access_relation": "{ comp01[i0, i1, i2] -> buf02[i0, i1] }",
                    "write_buffer_id": 2,
                    "data_type": "int32",
                    "data_type_size": 0,
                    "accesses": [
                        {
                            "access_is_reduction": true,
                            "buffer_id": 2,
                            "access_matrix": [
                                [
                                    1,
                                    0,
                                    0,
                                    0
                                ],
                                [
                                    0,
                                    1,
                                    0,
                                    -1
                                ]
                            ]
                        },
                        {
                            "access_is_reduction": true,
                            "buffer_id": 2,
                            "access_matrix": [
                                [
                                    1,
                                    0,
                                    0,
                                    0
                                ],
                                [
                                    0,
                                    1,
                                    0,
                                    0
                                ]
                            ]
                        },
                        {
                            "access_is_reduction": true,
                            "buffer_id": 2,
                            "access_matrix": [
                                [
                                    1,
                                    0,
                                    0,
                                    0
                                ],
                                [
                                    0,
                                    1,
                                    0,
                                    1
                                ]
                            ]
                        },
                        {
                            "access_is_reduction": true,
                            "buffer_id": 2,
                            "access_matrix": [
                                [
                                    1,
                                    0,
                                    0,
                                    -1
                                ],
                                [
                                    0,
                                    1,
                                    0,
                                    0
                                ]
                            ]
                        },
                        {
                            "access_is_reduction": true,
                            "buffer_id": 2,
                            "access_matrix": [
                                [
                                    1,
                                    0,
                                    0,
                                    1
                                ],
                                [
                                    0,
                                    1,
                                    0,
                                    0
                                ]
                            ]
                        }
                    ],
                    "expression_representation": {
                        "expr_type": "mul",
                        "children": [
                            {
                                "expr_type": "value",
                                "children": []
                            },
                            {
                                "expr_type": "sqrt",
                                "children": [
                                    {
                                        "expr_type": "sqrt",
                                        "children": [
                                            {
                                                "expr_type": "min",
                                                "children": [
                                                    {
                                                        "expr_type": "max",
                                                        "children": [
                                                            {
                                                                "expr_type": "access",
                                                                "children": []
                                                            },
                                                            {
                                                                "expr_type": "value",
                                                                "children": []
                                                            }
                                                        ]
                                                    },
                                                    {
                                                        "expr_type": "add",
                                                        "children": [
                                                            {
                                                                "expr_type": "sub",
                                                                "children": [
                                                                    {
                                                                        "expr_type": "add",
                                                                        "children": [
                                                                            {
                                                                                "expr_type": "sub",
                                                                                "children": [
                                                                                    {
                                                                                        "expr_type": "access",
                                                                                        "children": []
                                                                                    },
                                                                                    {
                                                                                        "expr_type": "mul",
                                                                                        "children": [
                                                                                            {
                                                                                                "expr_type": "value",
                                                                                                "children": []
                                                                                            },
                                                                                            {
                                                                                                "expr_type": "access",
                                                                                                "children": []
                                                                                            }
                                                                                        ]
                                                                                    }
                                                                                ]
                                                                            },
                                                                            {
                                                                                "expr_type": "access",
                                                                                "children": []
                                                                            }
                                                                        ]
                                                                    },
                                                                    {
                                                                        "expr_type": "mul",
                                                                        "children": [
                                                                            {
                                                                                "expr_type": "value",
                                                                                "children": []
                                                                            },
                                                                            {
                                                                                "expr_type": "access",
                                                                                "children": []
                                                                            }
                                                                        ]
                                                                    }
                                                                ]
                                                            },
                                                            {
                                                                "expr_type": "value",
                                                                "children": []
                                                            }
                                                        ]
                                                    }
                                                ]
                                            }
                                        ]
                                    }
                                ]
                            }
                        ]
                    }
                }
            }
        },
        "initial_execution_time": 0.019447,
        "schedules_list": [
            {
                "comp00": {
                    "shiftings": null,
                    "tiling": {},
                    "unrolling_factor": null,
                    "parallelized_dim": null,
                    "transformations_list": []
                },
                "comp01": {
                    "shiftings": null,
                    "tiling": {},
                    "unrolling_factor": null,
                    "parallelized_dim": null,
                    "transformations_list": []
                },
                "fusions": null,
                "sched_str": "",
                "tree_structure": {
                    "roots": [
                        {
                            "loop_name": "i0",
                            "computations_list": [],
                            "child_list": [
                                {
                                    "loop_name": "i1",
                                    "computations_list": [
                                        "comp00"
                                    ],
                                    "child_list": [
                                        {
                                            "loop_name": "i2",
                                            "computations_list": [
                                                "comp01"
                                            ],
                                            "child_list": []
                                        }
                                    ]
                                }
                            ]
                        }
                    ]
                },
                "legality_check": true,
                "exploration_method": 1,
                "execution_times": [
                    0.029376,
                    0.019447,
                    0.019492,
                    0.019532,
                    0.019503,
                    0.019505,
                    0.019488,
                    0.019505,
                    0.01949,
                    0.019507,
                    0.01949,
                    0.01952,
                    0.019483,
                    0.019524,
                    0.0195,
                    0.019519,
                    0.019518,
                    0.01949,
                    0.019487,
                    0.019516,
                    0.019522,
                    0.019489,
                    0.01949,
                    0.019523,
                    0.01951,
                    0.019515,
                    0.019508,
                    0.019512,
                    0.019507,
                    0.01947
                ]
            },
            {
                "comp00": {
                    "shiftings": null,
                    "tiling": {},
                    "unrolling_factor": null,
                    "parallelized_dim": null,
                    "transformations_list": [
                        [
                            1,
                            0,
                            1,
                            0,
                            0,
                            0,
                            0,
                            0,
                            0,
                            0,
                            0,
                            0,
                            0,
                            0,
                            0,
                            0
                        ]
                    ]
                },
                "comp01": {
                    "shiftings": null,
                    "tiling": {},
                    "unrolling_factor": null,
                    "parallelized_dim": null,
                    "transformations_list": [
                        [
                            1,
                            0,
                            1,
                            0,
                            0,
                            0,
                            0,
                            0,
                            0,
                            0,
                            0,
                            0,
                            0,
                            0,
                            0,
                            0
                        ]
                    ]
                },
                "fusions": null,
                "sched_str": "M({C0},0,1,1,0)M({C1},0,1,0,1,0,0,0,0,1)",
                "tree_structure": {
                    "roots": [
                        {
                            "loop_name": "i0",
                            "computations_list": [],
                            "child_list": [
                                {
                                    "loop_name": "i1",
                                    "computations_list": [
                                        "comp00"
                                    ],
                                    "child_list": [
                                        {
                                            "loop_name": "i2",
                                            "computations_list": [
                                                "comp01"
                                            ],
                                            "child_list": []
                                        }
                                    ]
                                }
                            ]
                        }
                    ]
                },
                "legality_check": true,
                "exploration_method": 1,
                "execution_times": [
                    0.017708,
                    0.01711,
                    0.017127,
                    0.01718,
                    0.017136,
                    0.017092,
                    0.017119,
                    0.017076,
                    0.017085,
                    0.017073,
                    0.017031,
                    0.01706,
                    0.017045,
                    0.017055,
                    0.017031,
                    0.017062,
                    0.017085,
                    0.017046,
                    0.01701,
                    0.017041,
                    0.01704,
                    0.017052,
                    0.01706,
                    0.01705,
                    0.017045,
                    0.017047,
                    0.017062,
                    0.01705,
                    0.017045,
                    0.01705
                ]
            },
            {
                "comp00": {
                    "shiftings": null,
                    "tiling": {},
                    "unrolling_factor": null,
                    "parallelized_dim": null,
                    "transformations_list": [
                        [
                            3,
                            0,
                            0,
                            0,
                            0,
                            1,
                            0,
                            1,
                            1,
                            0,
                            1,
                            0,
                            0,
                            0,
                            0,
                            0
                        ]
                    ]
                },
                "comp01": {
                    "shiftings": null,
                    "tiling": {},
                    "unrolling_factor": null,
                    "parallelized_dim": null,
                    "transformations_list": [
                        [
                            3,
                            0,
                            0,
                            0,
                            0,
                            1,
                            0,
                            1,
                            1,
                            0,
                            1,
                            0,
                            0,
                            0,
                            0,
                            0
                        ]
                    ]
                },
                "fusions": null,
                "sched_str": "M({C0},1,1,0,1)M({C1},1,1,0,0,1,0,0,0,1)",
                "tree_structure": {
                    "roots": [
                        {
                            "loop_name": "i0",
                            "computations_list": [],
                            "child_list": [
                                {
                                    "loop_name": "i1",
                                    "computations_list": [
                                        "comp00"
                                    ],
                                    "child_list": [
                                        {
                                            "loop_name": "i2",
                                            "computations_list": [
                                                "comp01"
                                            ],
                                            "child_list": []
                                        }
                                    ]
                                }
                            ]
                        }
                    ]
                },
                "legality_check": true,
                "exploration_method": 1,
                "execution_times": [
                    0.034549,
                    0.027988,
                    0.024046,
                    0.022377,
                    0.024265,
                    0.024156,
                    0.024103,
                    0.024029,
                    0.024454,
                    0.023821,
                    0.023832,
                    0.026497,
                    0.023943,
                    0.023964,
                    0.023916,
                    0.023819,
                    0.023882,
                    0.023911,
                    0.023903,
                    0.023861,
                    0.023922,
                    0.023867,
                    0.025173,
                    0.023929,
                    0.023882,
                    0.02394,
                    0.023928,
                    0.02397,
                    0.023793,
                    0.023856
                ]
            },
            {
                "comp00": {
                    "shiftings": null,
                    "tiling": {},
                    "unrolling_factor": null,
                    "parallelized_dim": null,
                    "transformations_list": [
                        [
                            3,
                            0,
                            0,
                            0,
                            0,
                            1,
                            0,
                            1,
                            2,
                            0,
                            1,
                            0,
                            0,
                            0,
                            0,
                            0
                        ]
                    ]
                },
                "comp01": {
                    "shiftings": null,
                    "tiling": {},
                    "unrolling_factor": null,
                    "parallelized_dim": null,
                    "transformations_list": [
                        [
                            3,
                            0,
                            0,
                            0,
                            0,
                            1,
                            0,
                            1,
                            2,
                            0,
                            1,
                            0,
                            0,
                            0,
                            0,
                            0
                        ]
                    ]
                },
                "fusions": null,
                "sched_str": "M({C0},1,2,0,1)M({C1},1,2,0,0,1,0,0,0,1)",
                "tree_structure": {
                    "roots": [
                        {
                            "loop_name": "i0",
                            "computations_list": [],
                            "child_list": [
                                {
                                    "loop_name": "i1",
                                    "computations_list": [
                                        "comp00"
                                    ],
                                    "child_list": [
                                        {
                                            "loop_name": "i2",
                                            "computations_list": [
                                                "comp01"
                                            ],
                                            "child_list": []
                                        }
                                    ]
                                }
                            ]
                        }
                    ]
                },
                "legality_check": true,
                "exploration_method": 1,
                "execution_times": [
                    0.014287,
                    0.013508,
                    0.028408,
                    0.013179,
                    0.013038,
                    0.013084,
                    0.013096,
                    0.013083,
                    0.01309,
                    0.013115,
                    0.013029,
                    0.013019,
                    0.013021,
                    0.013028,
                    0.013003,
                    0.013012,
                    0.012978,
                    0.013008,
                    0.013039,
                    0.013016,
                    0.013032,
                    0.013028,
                    0.013023,
                    0.01303,
                    0.013007,
                    0.013035,
                    0.013027,
                    0.01304,
                    0.013016,
                    0.013021
                ]
            },
            {
                "comp00": {
                    "shiftings": null,
                    "tiling": {},
                    "unrolling_factor": null,
                    "parallelized_dim": null,
                    "transformations_list": [
                        [
                            3,
                            0,
                            0,
                            0,
                            0,
                            1,
                            0,
                            1,
                            3,
                            0,
                            1,
                            0,
                            0,
                            0,
                            0,
                            0
                        ]
                    ]
                },
                "comp01": {
                    "shiftings": null,
                    "tiling": {},
                    "unrolling_factor": null,
                    "parallelized_dim": null,
                    "transformations_list": [
                        [
                            3,
                            0,
                            0,
                            0,
                            0,
                            1,
                            0,
                            1,
                            3,
                            0,
                            1,
                            0,
                            0,
                            0,
                            0,
                            0
                        ]
                    ]
                },
                "fusions": null,
                "sched_str": "M({C0},1,3,0,1)M({C1},1,3,0,0,1,0,0,0,1)",
                "tree_structure": {
                    "roots": [
                        {
                            "loop_name": "i0",
                            "computations_list": [],
                            "child_list": [
                                {
                                    "loop_name": "i1",
                                    "computations_list": [
                                        "comp00"
                                    ],
                                    "child_list": [
                                        {
                                            "loop_name": "i2",
                                            "computations_list": [
                                                "comp01"
                                            ],
                                            "child_list": []
                                        }
                                    ]
                                }
                            ]
                        }
                    ]
                },
                "legality_check": true,
                "exploration_method": 1,
                "execution_times": [
                    0.019988,
                    0.018278,
                    0.018235,
                    0.018264,
                    0.018258,
                    0.01824,
                    0.01819,
                    0.018082,
                    0.018158,
                    0.018133,
                    0.018118,
                    0.018158,
                    0.01808,
                    0.018068,
                    0.018122,
                    0.018149,
                    0.018159,
                    0.018052,
                    0.018,
                    0.018162,
                    0.018171,
                    0.018057,
                    0.018017,
                    0.018161,
                    0.018112,
                    0.018151,
                    0.01816,
                    0.01816,
                    0.018197,
                    0.018131
                ]
            },
            {
                "comp00": {
                    "shiftings": null,
                    "tiling": {},
                    "unrolling_factor": null,
                    "parallelized_dim": null,
                    "transformations_list": [
                        [
                            3,
                            0,
                            0,
                            0,
                            0,
                            1,
                            0,
                            1,
                            1,
                            1,
                            2,
                            0,
                            0,
                            0,
                            0,
                            0
                        ]
                    ]
                },
                "comp01": {
                    "shiftings": null,
                    "tiling": {},
                    "unrolling_factor": null,
                    "parallelized_dim": null,
                    "transformations_list": [
                        [
                            3,
                            0,
                            0,
                            0,
                            0,
                            1,
                            0,
                            1,
                            1,
                            1,
                            2,
                            0,
                            0,
                            0,
                            0,
                            0
                        ]
                    ]
                },
                "fusions": null,
                "sched_str": "M({C0},1,1,1,2)M({C1},1,1,0,1,2,0,0,0,1)",
                "tree_structure": {
                    "roots": [
                        {
                            "loop_name": "i0",
                            "computations_list": [],
                            "child_list": [
                                {
                                    "loop_name": "i1",
                                    "computations_list": [
                                        "comp00"
                                    ],
                                    "child_list": [
                                        {
                                            "loop_name": "i2",
                                            "computations_list": [
                                                "comp01"
                                            ],
                                            "child_list": []
                                        }
                                    ]
                                }
                            ]
                        }
                    ]
                },
                "legality_check": true,
                "exploration_method": 1,
                "execution_times": [
                    0.013818,
                    0.012737,
                    0.012676,
                    0.01275,
                    0.012603,
                    0.01258,
                    0.012606,
                    0.012599,
                    0.012554,
                    0.012565,
                    0.012529,
                    0.012565,
                    0.012574,
                    0.012582,
                    0.012558,
                    0.012564,
                    0.012569,
                    0.012562,
                    0.012591,
                    0.01256,
                    0.012562,
                    0.012546,
                    0.012584,
                    0.01256,
                    0.012553,
                    0.012542,
                    0.012555,
                    0.01256,
                    0.01258,
                    0.012561
                ]
            },
            {
                "comp00": {
                    "shiftings": null,
                    "tiling": {},
                    "unrolling_factor": null,
                    "parallelized_dim": null,
                    "transformations_list": [
                        [
                            3,
                            0,
                            0,
                            0,
                            0,
                            1,
                            0,
                            1,
                            2,
                            1,
                            3,
                            0,
                            0,
                            0,
                            0,
                            0
                        ]
                    ]
                },
                "comp01": {
                    "shiftings": null,
                    "tiling": {},
                    "unrolling_factor": null,
                    "parallelized_dim": null,
                    "transformations_list": [
                        [
                            3,
                            0,
                            0,
                            0,
                            0,
                            1,
                            0,
                            1,
                            2,
                            1,
                            3,
                            0,
                            0,
                            0,
                            0,
                            0
                        ]
                    ]
                },
                "fusions": null,
                "sched_str": "M({C0},1,2,1,3)M({C1},1,2,0,1,3,0,0,0,1)",
                "tree_structure": {
                    "roots": [
                        {
                            "loop_name": "i0",
                            "computations_list": [],
                            "child_list": [
                                {
                                    "loop_name": "i1",
                                    "computations_list": [
                                        "comp00"
                                    ],
                                    "child_list": [
                                        {
                                            "loop_name": "i2",
                                            "computations_list": [
                                                "comp01"
                                            ],
                                            "child_list": []
                                        }
                                    ]
                                }
                            ]
                        }
                    ]
                },
                "legality_check": true,
                "exploration_method": 1,
                "execution_times": [
                    0.017628,
                    0.015755,
                    0.015789,
                    0.015905,
                    0.01572,
                    0.015678,
                    0.015762,
                    0.015741,
                    0.015718,
                    0.01567,
                    0.015702,
                    0.015715,
                    0.01566,
                    0.01566,
                    0.015703,
                    0.015595,
                    0.015632,
                    0.015624,
                    0.015703,
                    0.015668,
                    0.015667,
                    0.015675,
                    0.015623,
                    0.015616,
                    0.01565,
                    0.015697,
                    0.015683,
                    0.01566,
                    0.015678,
                    0.015664
                ]
            },
            {
                "comp00": {
                    "shiftings": null,
                    "tiling": {},
                    "unrolling_factor": null,
                    "parallelized_dim": null,
                    "transformations_list": [
                        [
                            3,
                            0,
                            0,
                            0,
                            0,
                            1,
                            0,
                            1,
                            3,
                            1,
                            4,
                            0,
                            0,
                            0,
                            0,
                            0
                        ]
                    ]
                },
                "comp01": {
                    "shiftings": null,
                    "tiling": {},
                    "unrolling_factor": null,
                    "parallelized_dim": null,
                    "transformations_list": [
                        [
                            3,
                            0,
                            0,
                            0,
                            0,
                            1,
                            0,
                            1,
                            3,
                            1,
                            4,
                            0,
                            0,
                            0,
                            0,
                            0
                        ]
                    ]
                },
                "fusions": null,
                "sched_str": "M({C0},1,3,1,4)M({C1},1,3,0,1,4,0,0,0,1)",
                "tree_structure": {
                    "roots": [
                        {
                            "loop_name": "i0",
                            "computations_list": [],
                            "child_list": [
                                {
                                    "loop_name": "i1",
                                    "computations_list": [
                                        "comp00"
                                    ],
                                    "child_list": [
                                        {
                                            "loop_name": "i2",
                                            "computations_list": [
                                                "comp01"
                                            ],
                                            "child_list": []
                                        }
                                    ]
                                }
                            ]
                        }
                    ]
                },
                "legality_check": true,
                "exploration_method": 1,
                "execution_times": [
                    0.017059,
                    0.015963,
                    0.016048,
                    0.016055,
                    0.016033,
                    0.016026,
                    0.016017,
                    0.015958,
                    0.015913,
                    0.01591,
                    0.015951,
                    0.015927,
                    0.015977,
                    0.01593,
                    0.015947,
                    0.015946,
                    0.015955,
                    0.015963,
                    0.015946,
                    0.015902,
                    0.015935,
                    0.015932,
                    0.015967,
                    0.015963,
                    0.01593,
                    0.015925,
                    0.015927,
                    0.015923,
                    0.01592,
                    0.01593
                ]
            },
            {
                "comp00": {
                    "shiftings": null,
                    "tiling": {},
                    "unrolling_factor": null,
                    "parallelized_dim": null,
                    "transformations_list": [
                        [
                            3,
                            0,
                            0,
                            0,
                            0,
                            1,
                            0,
                            1,
                            0,
                            1,
                            1,
                            0,
                            0,
                            0,
                            0,
                            0
                        ]
                    ]
                },
                "comp01": {
                    "shiftings": null,
                    "tiling": {},
                    "unrolling_factor": null,
                    "parallelized_dim": null,
                    "transformations_list": [
                        [
                            3,
                            0,
                            0,
                            0,
                            0,
                            1,
                            0,
                            1,
                            0,
                            1,
                            1,
                            0,
                            0,
                            0,
                            0,
                            0
                        ]
                    ]
                },
                "fusions": null,
                "sched_str": "M({C0},1,0,1,1)M({C1},1,0,0,1,1,0,0,0,1)",
                "tree_structure": {
                    "roots": [
                        {
                            "loop_name": "i0",
                            "computations_list": [],
                            "child_list": [
                                {
                                    "loop_name": "i1",
                                    "computations_list": [
                                        "comp00"
                                    ],
                                    "child_list": [
                                        {
                                            "loop_name": "i2",
                                            "computations_list": [
                                                "comp01"
                                            ],
                                            "child_list": []
                                        }
                                    ]
                                }
                            ]
                        }
                    ]
                },
                "legality_check": true,
                "exploration_method": 1,
                "execution_times": [
                    0.038992,
                    0.026495,
                    0.031404,
                    0.026726,
                    0.01887,
                    0.018831,
                    0.018805,
                    0.018771,
                    0.018778,
                    0.018788,
                    0.018772,
                    0.018781,
                    0.018774,
                    0.026543,
                    0.026514,
                    0.02652,
                    0.026552,
                    0.026555,
                    0.026501,
                    0.026496,
                    0.02649,
                    0.026528,
                    0.026535,
                    0.026501,
                    0.026473,
                    0.026498,
                    0.026461,
                    0.02653,
                    0.026516,
                    0.026514
                ]
            },
            {
                "comp00": {
                    "shiftings": null,
                    "tiling": {},
                    "unrolling_factor": null,
                    "parallelized_dim": "i1",
                    "transformations_list": [
                        [
                            3,
                            0,
                            0,
                            0,
                            0,
                            1,
                            0,
                            1,
                            1,
                            1,
                            2,
                            0,
                            0,
                            0,
                            0,
                            0
                        ]
                    ]
                },
                "comp01": {
                    "shiftings": null,
                    "tiling": {},
                    "unrolling_factor": null,
                    "parallelized_dim": "i1",
                    "transformations_list": [
                        [
                            3,
                            0,
                            0,
                            0,
                            0,
                            1,
                            0,
                            1,
                            1,
                            1,
                            2,
                            0,
                            0,
                            0,
                            0,
                            0
                        ]
                    ]
                },
                "fusions": null,
                "sched_str": "M({C0},1,1,1,2)M({C1},1,1,0,1,2,0,0,0,1)P({C0,C1},L1)",
                "tree_structure": {
                    "roots": [
                        {
                            "loop_name": "i0",
                            "computations_list": [],
                            "child_list": [
                                {
                                    "loop_name": "i1",
                                    "computations_list": [
                                        "comp00"
                                    ],
                                    "child_list": [
                                        {
                                            "loop_name": "i2",
                                            "computations_list": [
                                                "comp01"
                                            ],
                                            "child_list": []
                                        }
                                    ]
                                }
                            ]
                        }
                    ]
                },
                "legality_check": true,
                "exploration_method": 1,
                "execution_times": [
                    4.57382,
                    2.78119,
                    2.00656,
                    2.10102,
                    1.5218,
                    1.81588,
                    1.57668,
                    1.84143,
                    1.63383,
                    1.56666,
                    1.39841,
                    1.68503,
                    1.71237,
                    1.66523,
                    1.65362,
                    1.80623,
                    1.7153,
                    1.86376,
                    1.93089,
                    2.27992,
                    1.48639,
                    1.84673,
                    2.17498,
                    1.97808,
                    1.64386,
                    1.80582,
                    1.49905,
                    1.56989,
                    1.61779,
                    1.78068
                ]
            },
            {
                "comp00": {
                    "shiftings": null,
                    "tiling": {},
                    "unrolling_factor": null,
                    "parallelized_dim": "i1",
                    "transformations_list": [
                        [
                            3,
                            0,
                            0,
                            0,
                            0,
                            1,
                            0,
                            1,
                            2,
                            0,
                            1,
                            0,
                            0,
                            0,
                            0,
                            0
                        ]
                    ]
                },
                "comp01": {
                    "shiftings": null,
                    "tiling": {},
                    "unrolling_factor": null,
                    "parallelized_dim": "i1",
                    "transformations_list": [
                        [
                            3,
                            0,
                            0,
                            0,
                            0,
                            1,
                            0,
                            1,
                            2,
                            0,
                            1,
                            0,
                            0,
                            0,
                            0,
                            0
                        ]
                    ]
                },
                "fusions": null,
                "sched_str": "M({C0},1,2,0,1)M({C1},1,2,0,0,1,0,0,0,1)P({C0,C1},L1)",
                "tree_structure": {
                    "roots": [
                        {
                            "loop_name": "i0",
                            "computations_list": [],
                            "child_list": [
                                {
                                    "loop_name": "i1",
                                    "computations_list": [
                                        "comp00"
                                    ],
                                    "child_list": [
                                        {
                                            "loop_name": "i2",
                                            "computations_list": [
                                                "comp01"
                                            ],
                                            "child_list": []
                                        }
                                    ]
                                }
                            ]
                        }
                    ]
                },
                "legality_check": true,
                "exploration_method": 1,
                "execution_times": [
                    3.68903,
                    2.05547,
                    1.81106,
                    1.57374,
                    1.53295,
                    1.73982,
                    1.70547,
                    1.56367,
                    1.57141,
                    1.4795,
                    1.63558,
                    1.8182,
                    1.99367,
                    1.81885,
                    1.83396,
                    1.6005,
                    1.68095,
                    1.49038,
                    1.62194,
                    1.66753,
                    1.56206,
                    1.52513,
                    1.77567,
                    1.42682,
                    1.23614,
                    1.27974,
                    1.70857,
                    1.49711,
                    1.50571,
                    1.69689
                ]
            }
        ],
        "exploration_trace": {
            "id": 0,
            "schedule": "",
            "depth": 1,
            "evaluation": 0.019447,
            "children": [
                {
                    "id": 0,
                    "schedule": "",
                    "depth": 1,
                    "evaluation": 0.019447,
                    "children": [
                        {
                            "id": 1,
                            "schedule": "M({C0},0,1,1,0)M({C1},0,1,0,1,0,0,0,0,1)",
                            "depth": 2,
                            "evaluation": 0.01701,
                            "children": []
                        },
                        {
                            "id": 2,
                            "schedule": "M({C0},1,1,0,1)M({C1},1,1,0,0,1,0,0,0,1)",
                            "depth": 2,
                            "evaluation": 0.022377,
                            "children": []
                        },
                        {
                            "id": 3,
                            "schedule": "M({C0},1,2,0,1)M({C1},1,2,0,0,1,0,0,0,1)",
                            "depth": 2,
                            "evaluation": 0.012978,
                            "children": [
                                {
                                    "id": 3,
                                    "schedule": "M({C0},1,2,0,1)M({C1},1,2,0,0,1,0,0,0,1)",
                                    "depth": 3,
                                    "evaluation": 0.012978,
                                    "children": [
                                        {
                                            "id": 10,
                                            "schedule": "M({C0},1,2,0,1)M({C1},1,2,0,0,1,0,0,0,1)P({C0,C1},L1)",
                                            "depth": 4,
                                            "evaluation": 1.23614,
                                            "children": []
                                        },
                                        {
                                            "id": 3,
                                            "schedule": "M({C0},1,2,0,1)M({C1},1,2,0,0,1,0,0,0,1)",
                                            "depth": 4,
                                            "evaluation": 0.012978,
                                            "children": []
                                        }
                                    ]
                                }
                            ]
                        },
                        {
                            "id": 4,
                            "schedule": "M({C0},1,3,0,1)M({C1},1,3,0,0,1,0,0,0,1)",
                            "depth": 2,
                            "evaluation": 0.018,
                            "children": []
                        },
                        {
                            "id": 5,
                            "schedule": "M({C0},1,1,1,2)M({C1},1,1,0,1,2,0,0,0,1)",
                            "depth": 2,
                            "evaluation": 0.012529,
                            "children": [
                                {
                                    "id": 5,
                                    "schedule": "M({C0},1,1,1,2)M({C1},1,1,0,1,2,0,0,0,1)",
                                    "depth": 3,
                                    "evaluation": 0.012529,
                                    "children": [
                                        {
                                            "id": 9,
                                            "schedule": "M({C0},1,1,1,2)M({C1},1,1,0,1,2,0,0,0,1)P({C0,C1},L1)",
                                            "depth": 4,
                                            "evaluation": 1.39841,
                                            "children": []
                                        },
                                        {
                                            "id": 5,
                                            "schedule": "M({C0},1,1,1,2)M({C1},1,1,0,1,2,0,0,0,1)",
                                            "depth": 4,
                                            "evaluation": 0.012529,
                                            "children": []
                                        }
                                    ]
                                }
                            ]
                        },
                        {
                            "id": 6,
                            "schedule": "M({C0},1,2,1,3)M({C1},1,2,0,1,3,0,0,0,1)",
                            "depth": 2,
                            "evaluation": 0.015595,
                            "children": [
                                {
                                    "id": 6,
                                    "schedule": "M({C0},1,2,1,3)M({C1},1,2,0,1,3,0,0,0,1)",
                                    "depth": 3,
                                    "evaluation": 0.015595,
                                    "children": [
                                        {
                                            "id": 11,
                                            "schedule": "M({C0},1,2,1,3)M({C1},1,2,0,1,3,0,0,0,1)P({C0,C1},L1)",
                                            "depth": 4,
                                            "evaluation": 1.31173,
                                            "children": []
                                        },
                                        {
                                            "id": 6,
                                            "schedule": "M({C0},1,2,1,3)M({C1},1,2,0,1,3,0,0,0,1)",
                                            "depth": 4,
                                            "evaluation": 0.015595,
                                            "children": []
                                        }
                                    ]
                                }
                            ]
                        },
                        {
                            "id": 7,
                            "schedule": "M({C0},1,3,1,4)M({C1},1,3,0,1,4,0,0,0,1)",
                            "depth": 2,
                            "evaluation": 0.015902,
                            "children": []
                        },
                        {
                            "id": 8,
                            "schedule": "M({C0},1,0,1,1)M({C1},1,0,0,1,1,0,0,0,1)",
                            "depth": 2,
                            "evaluation": 0.018771,
                            "children": []
                        },
                        {
                            "id": 0,
                            "schedule": "M({C0},1,0,0,1)M({C1},1,0,0,0,1,0,0,0,1)",
                            "depth": 2,
                            "evaluation": 0.019447,
                            "children": []
                        }
                    ]
                }
            ]
        }
    }
}